molmap/__init__.py
molmap/_base.py
molmap/agg.py
molmap/cpd.py
molmap/map.py
molmap/pdb.py
molmap/seq.py
molmap/show.py
molmap/config/__init__.py
molmap/config/descriptor_scale.cfg.gzip
molmap/config/fingerprint_scale.cfg.gzip
molmap/dataset/FreeSolv.csv
molmap/dataset/__init__.py
molmap/dataset/bace.csv
molmap/dataset/clintox.csv
molmap/dataset/delaney-processed.csv
molmap/feature/__init__.py
molmap/feature/descriptor/__init__.py
molmap/feature/descriptor/autocorr.py
molmap/feature/descriptor/charge.py
molmap/feature/descriptor/connectivity.py
molmap/feature/descriptor/constitution.py
molmap/feature/descriptor/estate.py
molmap/feature/descriptor/fragment.py
molmap/feature/descriptor/infocontent.py
molmap/feature/descriptor/kappa.py
molmap/feature/descriptor/matrix.py
molmap/feature/descriptor/moe.py
molmap/feature/descriptor/path.py
molmap/feature/descriptor/property.py
molmap/feature/descriptor/topology.py
molmap/feature/fingerprint/__init__.py
molmap/feature/fingerprint/atompairs.py
molmap/feature/fingerprint/avalonfp.py
molmap/feature/fingerprint/estatefp.py
molmap/feature/fingerprint/maccskeys.py
molmap/feature/fingerprint/maccskeys.xlsx
molmap/feature/fingerprint/map4.py
molmap/feature/fingerprint/mhfp6.py
molmap/feature/fingerprint/mnimalfatures.fdef
molmap/feature/fingerprint/morganfp.py
molmap/feature/fingerprint/pharmErGfp.py
molmap/feature/fingerprint/pharmPointfp.py
molmap/feature/fingerprint/pubchemfp.py
molmap/feature/fingerprint/pubchemfp.xlsx
molmap/feature/fingerprint/rdkitfp.py
molmap/feature/fingerprint/smarts_maccskey.py
molmap/feature/fingerprint/smarts_pharmacophore.py
molmap/feature/fingerprint/smarts_pubchem.py
molmap/feature/fingerprint/torsions.py
molmap/feature/sequence/__init__.py
molmap/feature/sequence/aas/__init__.py
molmap/feature/sequence/aas/global_feature/_AAComposition.py
molmap/feature/sequence/aas/global_feature/_Autocorrelation.py
molmap/feature/sequence/aas/global_feature/_CTD.py
molmap-1.4.0.dist-info/LICENSE
molmap-1.4.0.dist-info/METADATA
molmap-1.4.0.dist-info/WHEEL
molmap-1.4.0.dist-info/top_level.txt
molmap-1.4.0.dist-info/RECORD
