Metadata-Version: 2.1
Name: molmap
Version: 1.4.0
Summary: MolMap: An Efficient Convolutional Neural Network Based Molecular Deep Learning Tool
Home-page: https://github.com/shenwanxiang/bidd-molmap
Author: WanXiang Shen
License: UNKNOWN
Platform: UNKNOWN
Classifier: Programming Language :: Python :: 3
Classifier: License :: OSI Approved :: MIT License
Classifier: Operating System :: POSIX :: Linux
Classifier: Operating System :: Microsoft :: Windows
License-File: LICENSE
Requires-Dist: biopython (==1.78)
Requires-Dist: biopandas (==0.2.8)
Requires-Dist: seaborn (==0.9.1)
Requires-Dist: umap-learn (==0.3.10)
Requires-Dist: python-highcharts (==0.4.2)
Requires-Dist: pandas (==1.1.5)
Requires-Dist: colored (==1.3.93)
Requires-Dist: colorlog (==4.0.2)
Requires-Dist: mordred (==1.2.0)
Requires-Dist: gdown (==4.4.0)
Requires-Dist: mhfp (==1.9.2)
Requires-Dist: tensorflow-gpu (==2.9.1)
Requires-Dist: tensorflow (==2.9.1)
Requires-Dist: faerun
Requires-Dist: tqdm
Requires-Dist: scipy
Requires-Dist: numpy
Requires-Dist: numba
Requires-Dist: joblib
Requires-Dist: scikit-learn (==0.24)
Requires-Dist: lapjv
Provides-Extra: dev
Requires-Dist: pytest ; extra == 'dev'
